{
    "version": "https://jsonfeed.org/version/1",
    "title": "欢迎来到我的个人博客 • All posts by \"博客\" tag",
    "description": "",
    "home_page_url": "http://zhanglin233.github.io",
    "items": [
        {
            "id": "http://zhanglin233.github.io/2021/11/27/computer-science/blog/hexo-github%E9%83%A8%E7%BD%B2%E4%B8%AA%E4%BA%BA%E5%8D%9A%E5%AE%A2/",
            "url": "http://zhanglin233.github.io/2021/11/27/computer-science/blog/hexo-github%E9%83%A8%E7%BD%B2%E4%B8%AA%E4%BA%BA%E5%8D%9A%E5%AE%A2/",
            "title": "基于hexo框架部署个人博客",
            "date_published": "2021-11-26T17:22:09.498Z",
            "content_html": "<h1 id=\"基于hexo框架部署个人博客\"><a class=\"anchor\" href=\"#基于hexo框架部署个人博客\">#</a> 基于 hexo 框架部署个人博客</h1>\n<h2 id=\"起因\"><a class=\"anchor\" href=\"#起因\">#</a> 起因</h2>\n<h2 id=\"准备工作\"><a class=\"anchor\" href=\"#准备工作\">#</a> 准备工作</h2>\n<h3 id=\"git\"><a class=\"anchor\" href=\"#git\">#</a> git</h3>\n<h3 id=\"node\"><a class=\"anchor\" href=\"#node\">#</a> node</h3>\n<h3 id=\"hexo\"><a class=\"anchor\" href=\"#hexo\">#</a> hexo</h3>\n<h2 id=\"遇到的坑\"><a class=\"anchor\" href=\"#遇到的坑\">#</a> 遇到的坑</h2>\n<ol>\n<li>\n<p>首先遇到的第一个问题是</p>\n<figure class=\"highlight bash\"><figcaption data-lang=\"bash\"></figcaption><table><tr><td data-num=\"1\"></td><td><pre>The tag <span class=\"token variable\"><span class=\"token variable\">`</span>linksfile<span class=\"token variable\">`</span></span> on line <span class=\"token number\">23</span> <span class=\"token keyword\">in</span> <span class=\"token variable\"><span class=\"token variable\">`</span>source/friends/index.md<span class=\"token variable\">`</span></span> is not a recognized Liquid tag. For <span class=\"token function\">more</span> information, see https://docs.github.com/github/working-with-github-pages/troubleshooting-jekyll-build-errors-for-github-pages-sites<span class=\"token comment\">#unknown-tag-error.</span></pre></td></tr></table></figure><p>大概原因是 Jekyll 是一个静态站点生成器，内置 GitHub Pages 支持和简化的构建过程，官方建议将 Jekyll 用于 GitHub Pages。因此如果使用的不是 jekyll 框架，就可能会存在标签无法识别的情况。为了解决这样的问题，我们只需要在配置文件中禁用 jekyll 即可</p>\n<p>在博客项目根目录下添加空的.nojekyll 文件</p>\n<p><img data-src=\"https://gitee.com/nobody_heard_of_it/pic-md1/raw/master/image/20211126221143.png\" alt=\"\" /></p>\n<p>并在_config.yml 文件中加入以下配置即可：</p>\n<figure class=\"highlight yaml\"><figcaption data-lang=\"YAML\"></figcaption><table><tr><td data-num=\"1\"></td><td><pre><span class=\"token key atrule\">include</span><span class=\"token punctuation\">:</span></pre></td></tr><tr><td data-num=\"2\"></td><td><pre>  <span class=\"token punctuation\">-</span> .nojekyll</pre></td></tr></table></figure></li>\n<li>\n<p>第二个问题就是依据 hexo 官方文档</p>\n</li>\n<li>\n<p>spawn failed</p>\n</li>\n<li>\n<p>deploy :https 换 ssh</p>\n</li>\n<li>\n<p>RROR Deployer not found: git</p>\n</li>\n<li>\n<p>域名配置</p>\n</li>\n</ol>\n",
            "tags": [
                "博客"
            ]
        }
    ]
}